matter_task_queue/__about__.py
matter_task_queue/__init__.py
matter_task_queue/base_task.py
matter_task_queue/celery_config.py
matter_task_queue/config.py
matter_task_queue/utils.py
matter_task_queue-2.2.0.dist-info/METADATA
matter_task_queue-2.2.0.dist-info/WHEEL
matter_task_queue-2.2.0.dist-info/licenses/LICENSE
matter_task_queue-2.2.0.dist-info/RECORD
