Metadata-Version: 2.3
Name: matter-task-queue
Version: 2.2.0
Summary: A template for new Matter's library
Project-URL: Documentation, https://github.com/Matter-Tech/matter-task-queue#readme
Project-URL: Issues, https://github.com/Matter-Tech/matter-task-queue/issues
Project-URL: Source, https://github.com/Matter-Tech/matter-task-queue
Author-email: Tomer Sasson <tomer@thisismatter.com>
License-Expression: MIT
License-File: LICENSE
Classifier: Development Status :: 4 - Beta
Classifier: Programming Language :: Python
Classifier: Programming Language :: Python :: 3.10
Classifier: Programming Language :: Python :: 3.11
Classifier: Programming Language :: Python :: 3.12
Classifier: Programming Language :: Python :: Implementation :: CPython
Classifier: Programming Language :: Python :: Implementation :: PyPy
Requires-Python: >=3.10
Requires-Dist: celery[sqs]>=5.2.7
Requires-Dist: kombu>=5.2.4
Requires-Dist: matter-exceptions>=1.1.0
Provides-Extra: sentry
Requires-Dist: sentry-sdk>=1.23.1; extra == 'sentry'
